main.py
netmind_lolGPT-1.0.0.dist-info/LICENSE
netmind_lolGPT-1.0.0.dist-info/METADATA
netmind_lolGPT-1.0.0.dist-info/WHEEL
netmind_lolGPT-1.0.0.dist-info/entry_points.txt
netmind_lolGPT-1.0.0.dist-info/top_level.txt
netmind_lolGPT-1.0.0.dist-info/RECORD
