Metadata-Version: 2.1
Name: netmind-lolGPT
Version: 1.0.0
Summary: AI-powered League of Legends professional esports match predictor and summoner analysis tool. Predict outcomes for T1, Faker, Zeus, and other pro players with advanced statistical modeling.
Home-page: https://github.com/onepersonunicorn/lolgpt
Author: lolGPT Team
Author-email: lolGPT Team <faker@1tier.xyz>
Project-URL: Homepage, https://1tier.xyz
Project-URL: Repository, https://github.com/onepersonunicorn/lolgpt
Project-URL: Documentation, https://1tier.xyz
Keywords: mcp,league-of-legends,lol,summoner,mock-match,simulation,esports,gaming,riot-games,summoners-rift,prediction,pvp,comparison,professional-gaming,t1,faker,zeus,lck,lcs,worlds,msi,pro-player,esports-analytics,competitive-lol,team-analysis,player-stats,tournament-prediction
Classifier: Development Status :: 4 - Beta
Classifier: Intended Audience :: Developers
Classifier: License :: OSI Approved :: MIT License
Classifier: Programming Language :: Python :: 3
Classifier: Programming Language :: Python :: 3.10
Classifier: Programming Language :: Python :: 3.11
Classifier: Programming Language :: Python :: 3.12
Requires-Python: >=3.10
License-File: LICENSE
Requires-Dist: fastmcp>=0.1.0
Requires-Dist: requests>=2.28.0
